[{"text":"Indistractable","styles":"","link":"","id":"n9tO","outline":[{"text":"The problem","styles":"","link":"","id":"4wPr","outline":[{"text":"When attempting something difficult, there is discomfort","styles":"","link":"","id":"XAVe"},{"text":"Distraction is a way to avoid or delay discomfort","styles":"","link":"","id":"RU1B"},{"text":"Distracting behavior tends to be -","styles":"","link":"","id":"F6Nz","outline":[{"text":"- easy, not confusing","styles":"","link":"","id":"YgPd"},{"text":"- something I can control and succeed at ","styles":"","link":"","id":"Fnqw"},{"text":"- non-productive","styles":"","link":"","id":"ldXm"},{"text":"- may be productive but not urgent - do it later","styles":"","link":"","id":"ZUFR"},{"text":"- addicting","styles":"","link":"","id":"IKKA"}]},{"text":"How do I stay focused on a difficult task when escaping is so easy?","styles":"","link":"","id":"vY9a"}]},{"text":"Notice the details","styles":"","link":"","id":"SSjm","outline":[{"text":"How does distraction emerge in you?","styles":"","link":"","id":"ziB0"},{"text":"Notice the craving for the distracting behavior","styles":"","link":"","id":"OFwr"},{"text":"Look for the emotion and/or discomfort that precedes the distraction","styles":"","link":"","id":"lVLX"},{"text":"Such as anxiety, feeling restless, feeling incompetent, craving something","styles":"","link":"","id":"EwpZ"},{"text":"Take notes. Use Distraction Tracker sheet","styles":"","link":"","id":"u5ei"},{"text":"Be a witness - \"I feel a familiar tension in my chest. And I want to click on CNN.\"","styles":"","link":"","id":"qHmL"},{"text":"Do you experience a cycle of resisting, ruminating, and finally giving in to a desire?","styles":"","link":"","id":"DPuS"}]},{"text":"Ten minute rule","styles":"","link":"","id":"z-Jd","outline":[{"text":"It's dangerous to do some unhelpful behavior \"just for a second\"","styles":"","link":"","id":"Ecbp"},{"text":"I can do the thing but only after I wait ten minutes.","styles":"","link":"","id":"FM3_"},{"text":"During the ten minutes, notice your sensations and ride them like a wave ","styles":"","link":"","id":"5UIL"},{"text":"Don't push anything away and also don't act on anything","styles":"","link":"","id":"VOjd"},{"text":"Watch the craving as it crests and subsides","styles":"","link":"","id":"qYfJ"},{"text":"Imagine leaves floating down a stream. Place your thought on a leaf and let it float away, swirling in the current.","styles":"","link":"","id":"BLi5"}]},{"text":"What's interesting here?","styles":"","link":"","id":"URPT","outline":[{"text":"Approach a familiar situation with fresh eyes, curiosity, creativity, humor","styles":"","link":"","id":"GK3T"},{"text":"Pay full attention to find variability and challenges you didn't see before","styles":"","link":"","id":"ucdu"},{"text":"Pay close, foolish, even absurd attention to your task","styles":"","link":"","id":"Gjbo"},{"text":"Learn new things about it, transform it into an imaginary playground.","styles":"","link":"","id":"wIui"},{"text":"What is interesting about it that you didn't notice before?","styles":"","link":"","id":"ECrY"},{"text":"Find some aspect of the task that your mind can get hooked into","styles":"","link":"","id":"e-GJ"},{"text":"Pose interesting questions","styles":"","link":"","id":"IdPt"},{"text":"Look for new solutions to old problems","styles":"","link":"","id":"RHg4"},{"text":"What is mysterious about this? What do I want to know about this? What am I curious about?","styles":"","link":"","id":"r9Hc"},{"text":"Look for variability and novelty","styles":"","link":"","id":"RE2T"},{"text":"Do the task to a higher standard of excellence","styles":"","link":"","id":"XREi"},{"text":"Example - Mowing the lawn","styles":"","link":"","id":"qTwh","outline":[{"text":"How can I mow the lawn more efficiently?","styles":"","link":"","id":"W1k4"},{"text":"What is the optimum path for the mower?","styles":"","link":"","id":"W06C"},{"text":"Look for the interesting constraints","styles":"","link":"","id":"oDCB"},{"text":"Can you beat your record time?","styles":"","link":"","id":"aTMN"},{"text":"Understand how the grass grows and how to help it grow","styles":"","link":"","id":"K7Xq"}]}]},{"text":"Will power","styles":"","link":"","id":"QTUV","outline":[{"text":"You don't run out of will power","styles":"","link":"","id":"YOHa"},{"text":"It does ebb and flow but it's not out of control","styles":"","link":"","id":"6rqQ"},{"text":"You don't run out of calmness or excitement, likewise will power","styles":"","link":"","id":"e3xk"},{"text":"Is there a method to maximize will power?","styles":"","link":"","id":"MM17"},{"text":"Lack of motivation is temporary","styles":"","link":"","id":"ZiJo"}]},{"text":"Define your values","styles":"","link":"","id":"l_2G","outline":[{"text":"What vibration do you want to give to the world?","styles":"","link":"","id":"HWFF"},{"text":"What do you want to stand for?","styles":"","link":"","id":"BeaQ"},{"text":"How do you want to relate to the world?","styles":"","link":"","id":"HM73"},{"text":"What are the attributes of the person you want to be?","styles":"","link":"","id":"7byW"},{"text":"Create a schedule that includes activities aligned with your values","styles":"","link":"","id":"o_sj"}]}]}]